{
  "$schema": "https://developer.microsoft.com/json-schemas/spfx-build/package-solution.schema.json",
  "solution": {
    "name": "new-form-client-side-solution",
    "id": "b2c7a935-d76e-48e0-85ef-7c98d2b3f3d0",
    "version": "1.0.0.0",
    "includeClientSideAssets": true,
    "skipFeatureDeployment": true,
    "isDomainIsolated": false,
    "developer": {
      "name": "",
      "websiteUrl": "",
      "privacyUrl": "",
      "termsOfUseUrl": "",
      "mpnId": "Undefined-1.14.0"
    },
    "metadata": {
      "shortDescription": {
        "default": "new-form description"
      },
      "longDescription": {
        "default": "new-form description"
      },
      "screenshotPaths": [],
      "videoUrl": "",
      "categories": []
    },
    "features": [
      {
        "title": "new-form Feature",
        "description": "The feature that activates elements of the new-form solution.",
        "id": "7d882c8c-e444-4641-8249-25dad7743b9e",
        "version": "1.0.0.0"
      }
    ]
  },
  "paths": {
    "zippedPackage": "solution/new-form.sppkg"
  }
}
